marvolo/__init__.py
marvolo/cv.py
marvolo/decorator.py
marvolo/ffmpeg.py
marvolo/tools.py
marvolo-0.1.8.dist-info/METADATA
marvolo-0.1.8.dist-info/WHEEL
marvolo-0.1.8.dist-info/top_level.txt
marvolo-0.1.8.dist-info/RECORD
