Metadata-Version: 2.1
Name: marvolo
Version: 0.1.8
Summary: Some useful tools about CV develeped by Marvolo
Home-page: 
Author: Marvolo
Author-email: 18377221@buaa.edu.cn
License: MIT
Platform: all
Classifier: Programming Language :: Python :: 3
Classifier: License :: OSI Approved :: MIT License
Classifier: Operating System :: OS Independent
Requires-Python: >=3.6
Requires-Dist: opencv-python
Requires-Dist: imageio
Requires-Dist: numpy
Requires-Dist: imageio[ffmpeg]
